okkie/__init__.py
okkie/cli.py
okkie-0.1.1.dist-info/licenses/LICENSE
okkie-0.1.1.dist-info/METADATA
okkie-0.1.1.dist-info/WHEEL
okkie-0.1.1.dist-info/entry_points.txt
okkie-0.1.1.dist-info/top_level.txt
okkie-0.1.1.dist-info/RECORD
