Metadata-Version: 2.4
Name: okkie
Version: 0.1.1
Summary: Convert text into okkie language
Author-email: Chris van Meer <chris@van-meer.net>
Maintainer-email: Chris van Meer <chris@van-meer.net>
License: MIT
Project-URL: Homepage, https://github.com/chrisvanmeer/okkie
Project-URL: Repository, https://github.com/chrisvanmeer/okkie.git
Project-URL: Issues, https://github.com/chrisvanmeer/okkie/issues
Keywords: okkie,language
Requires-Python: >=3.8
License-File: LICENSE
Dynamic: license-file
